datapizza/vectorstores/qdrant/__init__.py
datapizza/vectorstores/qdrant/qdrant_vectorstore.py
datapizza/vectorstores/qdrant/tests/test_qdrant_vectorstore.py
datapizza_ai_vectorstores_qdrant-0.0.7.dist-info/METADATA
datapizza_ai_vectorstores_qdrant-0.0.7.dist-info/WHEEL
datapizza_ai_vectorstores_qdrant-0.0.7.dist-info/RECORD
