Metadata-Version: 2.4
Name: datapizza-ai-vectorstores-qdrant
Version: 0.0.7
Summary: Qdrant vectorstore for the datapizza-ai framework
License: MIT
Classifier: License :: OSI Approved :: MIT License
Classifier: Programming Language :: Python :: 3
Classifier: Topic :: Scientific/Engineering :: Artificial Intelligence
Classifier: Topic :: Software Development :: Libraries :: Application Frameworks
Requires-Python: <4,>=3.10.0
Requires-Dist: datapizza-ai-core<0.1.0,>=0.0.6
Requires-Dist: qdrant-client<2.0.0,>=1.16.0
